{
  "total": 6,
  "active": 6,
  "sample": [
    {
      "id": "1865c896-2048-439e-9643-1a3327127f32",
      "title": "Sayur",
      "active": true,
      "status": "ACTIVE",
      "deliveryAvailable": false,
      "sellerId": "5d5b64db-e1fe-41e6-87d7-de972fb61005",
      "seller": {
        "name": "Jane Seller",
        "sellerProfile": {
          "latitude": 3.1553301,
          "longitude": 101.7522384
        }
      }
    },
    {
      "id": "1e767077-e3db-45c4-8d2e-3e8b60ceee61",
      "title": "Cannabis",
      "active": true,
      "status": "ACTIVE",
      "deliveryAvailable": true,
      "sellerId": "880b9707-d4e6-4e3a-9387-0a1fd60f4ee3",
      "seller": {
        "name": "Wiz Khalifah",
        "sellerProfile": {
          "latitude": 3.2062633,
          "longitude": 101.581848
        }
      }
    },
    {
      "id": "2a380711-c5a1-4ed3-8540-5689d5c98d7a",
      "title": "Matcha",
      "active": true,
      "status": "ACTIVE",
      "deliveryAvailable": true,
      "sellerId": "4a1c68a1-7d3c-4380-a95a-1b31df4b5986",
      "seller": {
        "name": "Snopp Dogg Enterprise",
        "sellerProfile": {
          "latitude": 3.3621022,
          "longitude": 101.3455503
        }
      }
    },
    {
      "id": "bb095547-26ca-426f-ac3b-151f097ac73c",
      "title": "Depressant Cure",
      "active": true,
      "status": "ACTIVE",
      "deliveryAvailable": false,
      "sellerId": "880b9707-d4e6-4e3a-9387-0a1fd60f4ee3",
      "seller": {
        "name": "Wiz Khalifah",
        "sellerProfile": {
          "latitude": 3.2062633,
          "longitude": 101.581848
        }
      }
    },
    {
      "id": "e0881908-31dc-4dec-b81f-b7cfa3ee5441",
      "title": "California",
      "active": true,
      "status": "ACTIVE",
      "deliveryAvailable": true,
      "sellerId": "880b9707-d4e6-4e3a-9387-0a1fd60f4ee3",
      "seller": {
        "name": "Wiz Khalifah",
        "sellerProfile": {
          "latitude": 3.2062633,
          "longitude": 101.581848
        }
      }
    },
    {
      "id": "e9a805e1-0772-4630-ac31-85cd084c8c1f",
      "title": "Veggie",
      "active": true,
      "status": "ACTIVE",
      "deliveryAvailable": true,
      "sellerId": "5d5b64db-e1fe-41e6-87d7-de972fb61005",
      "seller": {
        "name": "Jane Seller",
        "sellerProfile": {
          "latitude": 3.1553301,
          "longitude": 101.7522384
        }
      }
    }
  ]
}